custom_image_builder/__init__.py
custom_image_builder/exception/ImageBuilderException.py
custom_image_builder/exception/RegisterImageException.py
custom_image_builder/exception/__init__.py
custom_image_builder/image_builder.py
custom_image_builder-1.0.1.dist-info/WHEEL
custom_image_builder-1.0.1.dist-info/METADATA
custom_image_builder-1.0.1.dist-info/RECORD
