Metadata-Version: 2.1
Name: custom-image-builder
Version: 1.0.1
Summary: A python package that enables user to build their custom singularity image on HPC cluster
Author: ritwik-deshpande
Author-email: ritwikdeshpande01@gmail.com
Requires-Python: >=3.9,<4.0
Classifier: Programming Language :: Python :: 3
Classifier: Programming Language :: Python :: 3.9
Classifier: Programming Language :: Python :: 3.10
Classifier: Programming Language :: Python :: 3.11
Requires-Dist: Jinja2 (==3.1.2)
Requires-Dist: MarkupSafe (==2.1.3)
Requires-Dist: PyJWT (==2.8.0)
Requires-Dist: certifi (==2023.7.22)
Requires-Dist: cffi (==1.15.1)
Requires-Dist: charset-normalizer (==3.2.0)
Requires-Dist: cryptography (==41.0.3)
Requires-Dist: globus-compute-sdk (==2.2.0)
Requires-Dist: idna (==3.4)
Requires-Dist: packaging (==23.1)
Requires-Dist: pika (==1.3.2)
Requires-Dist: pycparser (==2.21)
Requires-Dist: pydantic (==1.10.12)
Requires-Dist: requests (==2.31.0)
Requires-Dist: tblib (==1.7.0)
Requires-Dist: texttable (==1.6.7)
Requires-Dist: typing_extensions (==4.7.1)
Requires-Dist: urllib3 (==2.0.4)
Requires-Dist: websockets (==10.3)
